dash_mosaic/0293be2cbbfe7cf6d05d.ttf
dash_mosaic/07ceeaf651de3a2212ab.ttf
dash_mosaic/133278435c7e3a5c3384.woff
dash_mosaic/23.dash_mosaic.min.js
dash_mosaic/23.dash_mosaic.min.js.map
dash_mosaic/231.dash_mosaic.min.js
dash_mosaic/231.dash_mosaic.min.js.map
dash_mosaic/26acf6d9b4fee5c2109e.woff2
dash_mosaic/322.dash_mosaic.min.js
dash_mosaic/322.dash_mosaic.min.js.map
dash_mosaic/341fe54857c4d05eddd2.ttf
dash_mosaic/39ceefe175bf3ab3561a.svg
dash_mosaic/3ad8f9c8df16e59fdfe4.svg
dash_mosaic/3e4f07afd3cd18d3667c.woff
dash_mosaic/42799c46648835be2c4d.eot
dash_mosaic/44bd2603cddad1661435.svg
dash_mosaic/560b9615f7b3004aecbd.ttf
dash_mosaic/5868628a16a043a50c4e.woff2
dash_mosaic/58b8c2e52da6d57a1667.woff2
dash_mosaic/65d8ce7c46337d010170.woff
dash_mosaic/668d8e42ab470276d8e0.svg
dash_mosaic/672.dash_mosaic.min.js
dash_mosaic/672.dash_mosaic.min.js.map
dash_mosaic/6cc162310312fb13c3af.svg
dash_mosaic/709d5be26f3aade35cde.woff
dash_mosaic/783.dash_mosaic.min.js
dash_mosaic/783.dash_mosaic.min.js.map
dash_mosaic/7ea5a9dffbd4d062d0a6.woff2
dash_mosaic/824.dash_mosaic.min.js
dash_mosaic/824.dash_mosaic.min.js.map
dash_mosaic/825.dash_mosaic.min.js
dash_mosaic/825.dash_mosaic.min.js.map
dash_mosaic/860.dash_mosaic.min.js
dash_mosaic/860.dash_mosaic.min.js.map
dash_mosaic/88853c0bcf2930908a9c.eot
dash_mosaic/89d51475d84ace19ab73.svg
dash_mosaic/8b8b953515da42b76b79.eot
dash_mosaic/8b98ab98df5b2fce6f57.woff
dash_mosaic/9dca4330b295b2ec4c75.woff2
dash_mosaic/DashMosaic.py
dash_mosaic/__init__.py
dash_mosaic/_imports_.py
dash_mosaic/a16bd121d1b6a0a00cf1.svg
dash_mosaic/a529fd139dca0b413ff3.woff2
dash_mosaic/a6403ffa1b598996bc13.ttf
dash_mosaic/af064735c69948f0b4ed.woff
dash_mosaic/b6edc27e079a14f50004.ttf
dash_mosaic/b85a36d81d81146cea0f.svg
dash_mosaic/becf184923f4bb050876.woff
dash_mosaic/c69a770ca9e5ac20beea.eot
dash_mosaic/c85ac7243e463a12d94d.ttf
dash_mosaic/c9b7c8427aa11a3df239.woff2
dash_mosaic/cb211bb9ad57b25d9013.ttf
dash_mosaic/dash_mosaic.min.js
dash_mosaic-1.0.0.dist-info/licenses/LICENSE
dash_mosaic-1.0.0.dist-info/METADATA
dash_mosaic-1.0.0.dist-info/WHEEL
dash_mosaic-1.0.0.dist-info/top_level.txt
dash_mosaic-1.0.0.dist-info/RECORD
