Metadata-Version: 2.4
Name: dash-mosaic
Version: 1.0.0
Summary: A flexible, resizable, and draggable multi-pane layout component for Plotly Dash applications
Home-page: https://github.com/pip-install-python/dash-mosaic
Author: Pip Install Python <pipinstallpython@gmail.com>
Author-email: Pip Install Python <pipinstallpython@gmail.com>
License: MIT
Project-URL: Homepage, https://github.com/pip-install-python/dash-mosaic
Project-URL: Documentation, https://github.com/pip-install-python/dash-mosaic
Project-URL: Repository, https://github.com/pip-install-python/dash-mosaic
Project-URL: Bug Reports, https://github.com/pip-install-python/dash-mosaic/issues
Project-URL: Changelog, https://github.com/pip-install-python/dash-mosaic/blob/main/CHANGELOG.md
Keywords: dash,plotly,react,mosaic,layout,dashboard,multi-pane,resizable
Classifier: Development Status :: 5 - Production/Stable
Classifier: Intended Audience :: Developers
Classifier: Intended Audience :: Science/Research
Classifier: Intended Audience :: Financial and Insurance Industry
Classifier: Topic :: Software Development :: Libraries :: Python Modules
Classifier: Topic :: Software Development :: User Interfaces
Classifier: Topic :: Scientific/Engineering :: Visualization
Classifier: License :: OSI Approved :: MIT License
Classifier: Programming Language :: Python :: 3
Classifier: Programming Language :: Python :: 3.7
Classifier: Programming Language :: Python :: 3.8
Classifier: Programming Language :: Python :: 3.9
Classifier: Programming Language :: Python :: 3.10
Classifier: Programming Language :: Python :: 3.11
Classifier: Programming Language :: Python :: 3.12
Classifier: Framework :: Dash
Classifier: Operating System :: OS Independent
Classifier: Environment :: Web Environment
Requires-Python: >=3.7
License-File: LICENSE
Requires-Dist: dash>=2.0.0
Provides-Extra: dev
Requires-Dist: dash[dev]>=2.0.0; extra == "dev"
Requires-Dist: plotly>=5.0.0; extra == "dev"
Requires-Dist: numpy>=1.20.0; extra == "dev"
Requires-Dist: pytest>=6.0.0; extra == "dev"
Requires-Dist: black>=22.0.0; extra == "dev"
Requires-Dist: flake8>=4.0.0; extra == "dev"
Dynamic: author
Dynamic: home-page
Dynamic: license-file
Dynamic: requires-python
